grafoleancollector/__init__.py
grafoleancollector/collector.py
grafoleancollector-0.0.12.dist-info/LICENSE.md
grafoleancollector-0.0.12.dist-info/METADATA
grafoleancollector-0.0.12.dist-info/WHEEL
grafoleancollector-0.0.12.dist-info/top_level.txt
grafoleancollector-0.0.12.dist-info/RECORD
