Metadata-Version: 2.1
Name: grafoleancollector
Version: 0.0.12
Summary: Common utilities for creating (controlled) collectors for Grafolean
Home-page: https://gitlab.com/grafolean/grafolean-collector
Author: Anže Škerlavaj
Author-email: info@grafolean.com
License: Commons Clause + Apache 2.0
Platform: UNKNOWN
Requires-Dist: apscheduler (==3.6.1)
Requires-Dist: certifi (==2019.9.11)
Requires-Dist: chardet (==3.0.4)
Requires-Dist: idna (==2.8)
Requires-Dist: pytz (==2019.3)
Requires-Dist: requests (==2.22.0)
Requires-Dist: six (==1.12.0)
Requires-Dist: tzlocal (==2.0.0)
Requires-Dist: urllib3 (==1.25.6)
